apsfuncs/__init__.py
apsfuncs/GUI/BaseWidgets.py
apsfuncs/GUI/CustomWidgets.py
apsfuncs/GUI/MainWindowFile.py
apsfuncs/GUI/__init__.py
apsfuncs/GUI/Screens/CrashScreenFile.py
apsfuncs/GUI/Screens/FeedbackScreenFile.py
apsfuncs/GUI/Screens/LoadingScreen.py
apsfuncs/GUI/Screens/SettingsScreenFile.py
apsfuncs/GUI/Screens/__init__.py
apsfuncs/GUI/StyleSheets/BasicStyles.py
apsfuncs/GUI/StyleSheets/TitleThemeHandling.py
apsfuncs/GUI/StyleSheets/__init__.py
apsfuncs/Toolbox/AutoUpdating.py
apsfuncs/Toolbox/ConfigHandlers.py
apsfuncs/Toolbox/GlobalTools.py
apsfuncs/Toolbox/ProgSetup.py
apsfuncs/Toolbox/TemplateThreading.py
apsfuncs/Toolbox/TokenEncryper.py
apsfuncs/Toolbox/UpdateAuthentication.py
apsfuncs/Toolbox/__init__.py
apsfuncs/Toolbox/db_connections.py
apsfuncs/UpdateScripts/__init__.py
apsfuncs/UpdateScripts/cleanup.py
apsfuncs-1.1.9.dist-info/METADATA
apsfuncs-1.1.9.dist-info/WHEEL
apsfuncs-1.1.9.dist-info/licenses/LICENSE
apsfuncs-1.1.9.dist-info/RECORD
