Metadata-Version: 2.4
Name: apsfuncs
Version: 1.1.9
Summary: A container package holding general purpose tools and objects used by python programs supported by the Astrea Python Updater (APU) system
Project-URL: Homepage, https://github.com/Astrea-Bioseparations/apsfuncsRepo
Project-URL: Issues, https://github.com/Astrea-Bioseparations/apsfuncsRepo/issues
Author-email: Nathaniel Hughes <nj.hughes@astrea-bio.com>
License-Expression: GPL-3.0-or-later
License-File: LICENSE
Keywords: aps,astrea
Classifier: Operating System :: Microsoft :: Windows
Classifier: Programming Language :: Python :: 3
Requires-Python: >=3.9
Requires-Dist: cryptography
Requires-Dist: matplotlib
Requires-Dist: psycopg[binary]
Requires-Dist: pyqt6
